kernreg/__init__.py
kernreg/bandwidth_selection.py
kernreg/config.py
kernreg/example_data/motorcycle.dta
kernreg/funcs_to_jit.py
kernreg/linear_binning.py
kernreg/smooth.py
kernreg/utils.py
kernreg/visualize.py
kernreg-0.0.9.dist-info/LICENSE
kernreg-0.0.9.dist-info/WHEEL
kernreg-0.0.9.dist-info/METADATA
kernreg-0.0.9.dist-info/RECORD
