Metadata-Version: 2.1
Name: kernreg
Version: 0.0.9
Summary: Tool for non-parametric curve fitting using local polynomials.
Home-page: https://github.com/segsell/kernreg
License: MIT
Keywords: curve-fitting,non-parametric,local-polynomial-regression,kernel-regression
Author: Sebastian Gsell
Author-email: sebastian.gsell93@gmail.com
Requires-Python: >=3.7.1,<3.9
Classifier: License :: OSI Approved :: MIT License
Classifier: Programming Language :: Python :: 3
Classifier: Programming Language :: Python :: 3.8
Requires-Dist: matplotlib (>=3.3.3,<4.0.0)
Requires-Dist: mypy-extensions (>=0.4.3,<0.5.0)
Requires-Dist: numba (>=0.52.0,<0.53.0)
Requires-Dist: numpy (>=1.19.5,<2.0.0)
Requires-Dist: pandas (>=1.2.0,<2.0.0)
Project-URL: Repository, https://github.com/segsell/kernreg
